{"version":1,"resource":"file:///c%3A/Users/paafff/Desktop/devp/projectOlshop_MongoDB/Alpha/frontend/src/components/CartProduct.jsx","entries":[{"id":"ROJb.jsx","timestamp":1692801944538},{"id":"woxH.jsx","timestamp":1692802005158},{"id":"IVp3.jsx","timestamp":1692802132052},{"id":"jcU1.jsx","timestamp":1692802280687},{"id":"5iyd.jsx","timestamp":1692802341159},{"id":"dtOA.jsx","timestamp":1692802357886},{"id":"Um2h.jsx","timestamp":1692804528287},{"id":"q786.jsx","timestamp":1692804696844},{"id":"TJYY.jsx","timestamp":1692804725472},{"id":"50G8.jsx","timestamp":1692804747441},{"id":"EJ7x.jsx","timestamp":1692805616093},{"id":"FzuO.jsx","timestamp":1692805637157},{"id":"GecY.jsx","timestamp":1692805648489},{"id":"FEgT.jsx","timestamp":1692805968625},{"id":"YzHy.jsx","source":"undoRedo.source","timestamp":1692805976693},{"id":"ehr3.jsx","timestamp":1692806006905}]}