{"version":1,"resource":"file:///c%3A/Users/paafff/Desktop/devp/github/macro-project-IL/src/components/LoginForm.jsx","entries":[{"id":"843A.jsx","timestamp":1695045936564},{"id":"uksm.jsx","source":"undoRedo.source","timestamp":1695045938785},{"id":"yoGR.jsx","timestamp":1695046213961},{"id":"24eY.jsx","timestamp":1695293404522},{"id":"Hmkq.jsx","timestamp":1695293439155},{"id":"B9uh.jsx","timestamp":1695293590573},{"id":"qBoU.jsx","timestamp":1695293613824},{"id":"B8hC.jsx","timestamp":1695293625517},{"id":"te3p.jsx","timestamp":1695298531869}]}